mermaid_rs/__init__.py
mermaid_rs/__init__.pyi
mermaid_rs/mermaid_rs.cpython-312-darwin.so
mermaid_rs/py.typed
mermaid_rs-0.1.1.dist-info/METADATA
mermaid_rs-0.1.1.dist-info/WHEEL
mermaid_rs-0.1.1.dist-info/licenses/LICENSE
mermaid_rs-0.1.1.dist-info/RECORD
