Metadata-Version: 2.4
Name: mermaid-rs
Version: 0.1.1
Classifier: Development Status :: 3 - Alpha
Classifier: Intended Audience :: Developers
Classifier: License :: OSI Approved :: MIT License
Classifier: Programming Language :: Python :: 3
Classifier: Programming Language :: Python :: 3.12
Classifier: Programming Language :: Python :: 3.13
Classifier: Programming Language :: Python :: 3.14
Classifier: Programming Language :: Rust
Classifier: Topic :: Software Development :: Libraries :: Python Modules
Classifier: Topic :: Multimedia :: Graphics
Classifier: Topic :: Text Processing :: Markup
Requires-Dist: pytest>=8.0 ; extra == 'dev'
Provides-Extra: dev
License-File: LICENSE
Summary: Python bindings for mermaid-rs-renderer - Fast Mermaid diagram rendering in Rust
Keywords: mermaid,diagram,svg,renderer,rust,visualization
Author: Philipp Temminghoff
Requires-Python: >=3.12
Project-URL: Homepage, https://github.com/phil65/python-mermaid-rs
Project-URL: Issues, https://github.com/phil65/python-mermaid-rs/issues
Project-URL: Repository, https://github.com/phil65/python-mermaid-rs
